{
  "project_info": {
    "project_number": "994634378279",
    "project_id": "jhjhj-99c05",
    "storage_bucket": "jhjhj-99c05.appspot.com"
  },
  "client": [
    {
      "client_info": {
        "mobilesdk_app_id": "1:994634378279:android:e95b37bcf91efd1a557202",
        "android_client_info": {
          "package_name": "com.example.property"
        }
      },
      "oauth_client": [
        {
          "client_id": "994634378279-jbafhkmvk7n1ncf6s26jc44067rhtepu.apps.googleusercontent.com",
          "client_type": 3
        }
      ],
      "api_key": [
        {
          "current_key": "AIzaSyDR6I9UKhN7n0z3jtTsUrCoGhXf6klfc60"
        }
      ],
      "services": {
        "appinvite_service": {
          "other_platform_oauth_client": [
            {
              "client_id": "994634378279-jbafhkmvk7n1ncf6s26jc44067rhtepu.apps.googleusercontent.com",
              "client_type": 3
            }
          ]
        }
      }
    }
  ],
  "configuration_version": "1"
}